airflow/providers/redis/__init__.py
airflow/providers/redis/get_provider_info.py
airflow/providers/redis/version_compat.py
airflow/providers/redis/hooks/__init__.py
airflow/providers/redis/hooks/redis.py
airflow/providers/redis/log/__init__.py
airflow/providers/redis/log/redis_task_handler.py
airflow/providers/redis/operators/__init__.py
airflow/providers/redis/operators/redis_publish.py
airflow/providers/redis/queues/__init__.py
airflow/providers/redis/queues/redis.py
airflow/providers/redis/sensors/__init__.py
airflow/providers/redis/sensors/redis_key.py
airflow/providers/redis/sensors/redis_pub_sub.py
airflow/providers/redis/triggers/__init__.py
airflow/providers/redis/triggers/redis_await_message.py
apache_airflow_providers_redis-4.4.2.dist-info/entry_points.txt
apache_airflow_providers_redis-4.4.2.dist-info/licenses/LICENSE
apache_airflow_providers_redis-4.4.2.dist-info/licenses/NOTICE
apache_airflow_providers_redis-4.4.2.dist-info/WHEEL
apache_airflow_providers_redis-4.4.2.dist-info/METADATA
apache_airflow_providers_redis-4.4.2.dist-info/RECORD
