Metadata-Version: 2.4
Name: apache-airflow-providers-redis
Version: 4.4.2
Summary: Provider package apache-airflow-providers-redis for Apache Airflow
Keywords: airflow-provider,redis,airflow,integration
Author-email: Apache Software Foundation <dev@airflow.apache.org>
Maintainer-email: Apache Software Foundation <dev@airflow.apache.org>
Requires-Python: >=3.10
License-Expression: Apache-2.0
Classifier: Development Status :: 5 - Production/Stable
Classifier: Environment :: Console
Classifier: Environment :: Web Environment
Classifier: Intended Audience :: Developers
Classifier: Intended Audience :: System Administrators
Classifier: Framework :: Apache Airflow
Classifier: Framework :: Apache Airflow :: Provider
Classifier: Programming Language :: Python :: 3.10
Classifier: Programming Language :: Python :: 3.11
Classifier: Programming Language :: Python :: 3.12
Classifier: Programming Language :: Python :: 3.13
Classifier: Topic :: System :: Monitoring
License-File: LICENSE
License-File: NOTICE
Requires-Dist: apache-airflow>=2.11.0
Requires-Dist: apache-airflow-providers-common-compat>=1.12.0
Requires-Dist: redis>=4.5.2,!=4.5.5,!=5.0.2
Requires-Dist: apache-airflow-providers-common-messaging>=2.0.0 ; extra == "common-messaging"
Project-URL: Bug Tracker, https://github.com/apache/airflow/issues
Project-URL: Changelog, https://airflow.apache.org/docs/apache-airflow-providers-redis/4.4.2/changelog.html
Project-URL: Documentation, https://airflow.apache.org/docs/apache-airflow-providers-redis/4.4.2
Project-URL: Mastodon, https://fosstodon.org/@airflow
Project-URL: Slack Chat, https://s.apache.org/airflow-slack
Project-URL: Source Code, https://github.com/apache/airflow
Project-URL: YouTube, https://www.youtube.com/channel/UCSXwxpWZQ7XZ1WL3wqevChA/
Provides-Extra: common-messaging
